LICENSE.txt
MANIFEST.in
README.txt
setup.py
check_arg/__init__.py
check_arg/test_valid.py
check_arg.egg-info/PKG-INFO
check_arg.egg-info/SOURCES.txt
check_arg.egg-info/dependency_links.txt
check_arg.egg-info/top_level.txt