Metadata-Version: 1.1
Name: check-arg
Version: 0.1.3
Summary: wrapping decorator to enhance the documentation
Home-page: http://github.org/jul/check_arg
Author: Julien Tayon
Author-email: julien@tayon.net
License: License :: OSI Approved :: BSD License
Platform: UNKNOWN
Classifier: Development Status :: 4 - Beta
Classifier: Intended Audience :: Developers
Classifier: License :: OSI Approved :: Python Software Foundation License
Classifier: Programming Language :: Python :: 2.7
Classifier: Programming Language :: Python :: 3.2
Classifier: Operating System :: OS Independent
Classifier: Programming Language :: Python
